MdnJavascriptCankaoWendang201726/README.md
MdnJavascriptCankaoWendang201726/__init__.py
MdnJavascriptCankaoWendang201726/__main__.py
MdnJavascriptCankaoWendang201726/file.epub
MdnJavascriptCankaoWendang201726/index.html
MdnJavascriptCankaoWendang201726/css/__init__.py
MdnJavascriptCankaoWendang201726/css/annotations.css
MdnJavascriptCankaoWendang201726/css/main.css
MdnJavascriptCankaoWendang201726/css/normalize.css
MdnJavascriptCankaoWendang201726/css/popup.css
MdnJavascriptCankaoWendang201726/font/__init__.py
MdnJavascriptCankaoWendang201726/font/fontello.eot
MdnJavascriptCankaoWendang201726/font/fontello.svg
MdnJavascriptCankaoWendang201726/font/fontello.ttf
MdnJavascriptCankaoWendang201726/font/fontello.woff
MdnJavascriptCankaoWendang201726/img/__init__.py
MdnJavascriptCankaoWendang201726/img/annotator-glyph-sprite.png
MdnJavascriptCankaoWendang201726/img/annotator-icon-sprite.png
MdnJavascriptCankaoWendang201726/img/apple-touch-icon.png
MdnJavascriptCankaoWendang201726/img/cancelfullscreen.png
MdnJavascriptCankaoWendang201726/img/close.png
MdnJavascriptCankaoWendang201726/img/fullscreen.png
MdnJavascriptCankaoWendang201726/img/loader.gif
MdnJavascriptCankaoWendang201726/img/menu-icon.png
MdnJavascriptCankaoWendang201726/img/save.png
MdnJavascriptCankaoWendang201726/img/saved.png
MdnJavascriptCankaoWendang201726/img/settings-s.png
MdnJavascriptCankaoWendang201726/img/settings.png
MdnJavascriptCankaoWendang201726/img/star.png
MdnJavascriptCankaoWendang201726/js/__init__.py
MdnJavascriptCankaoWendang201726/js/epub.js
MdnJavascriptCankaoWendang201726/js/epub.min.js
MdnJavascriptCankaoWendang201726/js/epub.min.map
MdnJavascriptCankaoWendang201726/js/hooks.min.js
MdnJavascriptCankaoWendang201726/js/hooks.min.map
MdnJavascriptCankaoWendang201726/js/reader.js
MdnJavascriptCankaoWendang201726/js/reader.js.map
MdnJavascriptCankaoWendang201726/js/reader.min.js
MdnJavascriptCankaoWendang201726/js/reader.min.map
MdnJavascriptCankaoWendang201726/js/hooks/__init__.py
mdn_javascript_cankao_wendang_2017_2_6-2024.3.2.0.dist-info/METADATA
mdn_javascript_cankao_wendang_2017_2_6-2024.3.2.0.dist-info/WHEEL
mdn_javascript_cankao_wendang_2017_2_6-2024.3.2.0.dist-info/entry_points.txt
mdn_javascript_cankao_wendang_2017_2_6-2024.3.2.0.dist-info/top_level.txt
mdn_javascript_cankao_wendang_2017_2_6-2024.3.2.0.dist-info/RECORD
